Metadata-Version: 2.1
Name: seadu
Version: 0.1.1
Summary: Seafile Downloader and Uploader
Home-page: https://github.com/veoco/seadu
Author: Veoco
Author-email: one@nomox.cn
Classifier: Programming Language :: Python :: 3
Classifier: License :: OSI Approved :: GNU General Public License v2 (GPLv2)
License-File: LICENSE
Requires-Dist: aiohttp
Requires-Dist: tqdm
